liteiclink/__init__.py
liteiclink/transceiver.py
liteiclink/serdes/__init__.py
liteiclink/serdes/clock_aligner.py
liteiclink/serdes/common.py
liteiclink/serdes/gth3_ultrascale.py
liteiclink/serdes/gth4_ultrascale.py
liteiclink/serdes/gth_7series.py
liteiclink/serdes/gth_7series_init.py
liteiclink/serdes/gth_ultrascale.py
liteiclink/serdes/gth_ultrascale_init.py
liteiclink/serdes/gtp_7series.py
liteiclink/serdes/gtp_7series_init.py
liteiclink/serdes/gtx_7series.py
liteiclink/serdes/gtx_7series_init.py
liteiclink/serdes/gty_ultrascale.py
liteiclink/serdes/gty_ultrascale_init.py
liteiclink/serdes/serdes_ecp5.py
liteiclink/serwb/__init__.py
liteiclink/serwb/core.py
liteiclink/serwb/datapath.py
liteiclink/serwb/efinixserdes.py
liteiclink/serwb/etherbone.py
liteiclink/serwb/genphy.py
liteiclink/serwb/kuserdes.py
liteiclink/serwb/packet.py
liteiclink/serwb/phy.py
liteiclink/serwb/s7serdes.py
liteiclink/serwb/scrambler.py
liteiclink-2024.12.dist-info/licenses/LICENSE
liteiclink-2024.12.dist-info/METADATA
liteiclink-2024.12.dist-info/WHEEL
liteiclink-2024.12.dist-info/top_level.txt
liteiclink-2024.12.dist-info/RECORD
